{
  "address": "2SLgYEkzcZfHeZqhssWJSxC4w8pyLheFjj275z1QtYXY",
  "metadata": {
    "name": "real_estate_tokenization",
    "version": "0.1.0",
    "spec": "0.1.0",
    "description": "Created with Anchor"
  },
  "instructions": [
    {
      "name": "approve_user",
      "discriminator": [
        62,
        2,
        57,
        73,
        112,
        114,
        126,
        68
      ],
      "accounts": [
        {
          "name": "admin",
          "writable": true,
          "signer": true
        },
        {
          "name": "user_to_approve"
        },
        {
          "name": "kyc_entry",
          "writable": true,
          "pda": {
            "seeds": [
              {
                "kind": "const",
                "value": [
                  107,
                  121,
                  99
                ]
              },
              {
                "kind": "account",
                "path": "user_to_approve"
              }
            ]
          }
        },
        {
          "name": "system_program",
          "address": "11111111111111111111111111111111"
        }
      ],
      "args": []
    },
    {
      "name": "buy_shares",
      "discriminator": [
        40,
        239,
        138,
        154,
        8,
        37,
        106,
        108
      ],
      "accounts": [
        {
          "name": "buyer",
          "writable": true,
          "signer": true
        },
        {
          "name": "receiver"
        },
        {
          "name": "property_config",
          "writable": true,
          "pda": {
            "seeds": [
              {
                "kind": "const",
                "value": [
                  99,
                  111,
                  110,
                  102,
                  105,
                  103
                ]
              },
              {
                "kind": "arg",
                "path": "property_id"
              }
            ]
          }
        },
        {
          "name": "kyc_entry",
          "pda": {
            "seeds": [
              {
                "kind": "const",
                "value": [
                  107,
                  121,
                  99
                ]
              },
              {
                "kind": "account",
                "path": "receiver"
              }
            ]
          }
        },
        {
          "name": "mint",
          "writable": true,
          "pda": {
            "seeds": [
              {
                "kind": "const",
                "value": [
                  112,
                  114,
                  111,
                  112,
                  101,
                  114,
                  116,
                  121,
                  95,
                  109,
                  105,
                  110,
                  116
                ]
              },
              {
                "kind": "arg",
                "path": "property_id"
              }
            ]
          }
        },
        {
          "name": "receiver_ata",
          "writable": true
        },
        {
          "name": "token_program",
          "address": "TokenkegQfeZyiNwAJbNbGKPFXCWuBvf9Ss623VQ5DA"
        },
        {
          "name": "system_program",
          "address": "11111111111111111111111111111111"
        }
      ],
      "args": [
        {
          "name": "property_id",
          "type": "u64"
        },
        {
          "name": "amount_of_shares",
          "type": "u64"
        }
      ]
    },
    {
      "name": "initialize_property",
      "discriminator": [
        94,
        188,
        21,
        36,
        186,
        50,
        195,
        141
      ],
      "accounts": [
        {
          "name": "admin",
          "writable": true,
          "signer": true
        },
        {
          "name": "property_config",
          "writable": true,
          "pda": {
            "seeds": [
              {
                "kind": "const",
                "value": [
                  99,
                  111,
                  110,
                  102,
                  105,
                  103
                ]
              },
              {
                "kind": "arg",
                "path": "property_id"
              }
            ]
          }
        },
        {
          "name": "mint",
          "writable": true,
          "pda": {
            "seeds": [
              {
                "kind": "const",
                "value": [
                  112,
                  114,
                  111,
                  112,
                  101,
                  114,
                  116,
                  121,
                  95,
                  109,
                  105,
                  110,
                  116
                ]
              },
              {
                "kind": "arg",
                "path": "property_id"
              }
            ]
          }
        },
        {
          "name": "treasury",
          "pda": {
            "seeds": [
              {
                "kind": "const",
                "value": [
                  116,
                  114,
                  101,
                  97,
                  115,
                  117,
                  114,
                  121
                ]
              }
            ]
          }
        },
        {
          "name": "token_program",
          "address": "TokenkegQfeZyiNwAJbNbGKPFXCWuBvf9Ss623VQ5DA"
        },
        {
          "name": "system_program",
          "address": "11111111111111111111111111111111"
        }
      ],
      "args": [
        {
          "name": "property_id",
          "type": "u64"
        },
        {
          "name": "price_per_share",
          "type": "u64"
        },
        {
          "name": "max_shares",
          "type": "u64"
        }
      ]
    },
    {
      "name": "revoke_user",
      "discriminator": [
        218,
        157,
        199,
        179,
        146,
        143,
        101,
        25
      ],
      "accounts": [
        {
          "name": "admin",
          "writable": true,
          "signer": true
        },
        {
          "name": "user_to_revoke"
        },
        {
          "name": "kyc_entry",
          "writable": true,
          "pda": {
            "seeds": [
              {
                "kind": "const",
                "value": [
                  107,
                  121,
                  99
                ]
              },
              {
                "kind": "account",
                "path": "user_to_revoke"
              }
            ]
          }
        }
      ],
      "args": []
    },
    {
      "name": "withdraw_capital",
      "discriminator": [
        82,
        32,
        82,
        118,
        160,
        116,
        65,
        104
      ],
      "accounts": [
        {
          "name": "admin",
          "writable": true,
          "signer": true,
          "relations": [
            "property_config"
          ]
        },
        {
          "name": "property_config",
          "pda": {
            "seeds": [
              {
                "kind": "const",
                "value": [
                  99,
                  111,
                  110,
                  102,
                  105,
                  103
                ]
              },
              {
                "kind": "arg",
                "path": "property_id"
              }
            ]
          }
        },
        {
          "name": "treasury",
          "writable": true,
          "pda": {
            "seeds": [
              {
                "kind": "const",
                "value": [
                  116,
                  114,
                  101,
                  97,
                  115,
                  117,
                  114,
                  121
                ]
              }
            ]
          }
        },
        {
          "name": "system_program",
          "address": "11111111111111111111111111111111"
        }
      ],
      "args": [
        {
          "name": "_property_id",
          "type": "u64"
        },
        {
          "name": "amount",
          "type": "u64"
        }
      ]
    }
  ],
  "accounts": [
    {
      "name": "KycEntry",
      "discriminator": [
        43,
        113,
        165,
        70,
        7,
        3,
        232,
        8
      ]
    },
    {
      "name": "PropertyConfig",
      "discriminator": [
        142,
        96,
        246,
        238,
        68,
        165,
        215,
        34
      ]
    }
  ],
  "errors": [
    {
      "code": 6000,
      "name": "Unauthorized",
      "msg": "Unauthorized access"
    },
    {
      "code": 6001,
      "name": "SupplyLimitReached",
      "msg": "Supply limit reached for this property"
    },
    {
      "code": 6002,
      "name": "Overflow",
      "msg": "Math overflow"
    },
    {
      "code": 6003,
      "name": "UserNotKycVerified",
      "msg": "Receiver is not KYC verified/Whitelisted"
    },
    {
      "code": 6004,
      "name": "InsufficientFunds",
      "msg": "Insufficient funds in treasury"
    }
  ],
  "types": [
    {
      "name": "KycEntry",
      "type": {
        "kind": "struct",
        "fields": [
          {
            "name": "user",
            "type": "pubkey"
          },
          {
            "name": "is_verified",
            "type": "bool"
          }
        ]
      }
    },
    {
      "name": "PropertyConfig",
      "type": {
        "kind": "struct",
        "fields": [
          {
            "name": "property_id",
            "type": "u64"
          },
          {
            "name": "admin",
            "type": "pubkey"
          },
          {
            "name": "price_per_share",
            "type": "u64"
          },
          {
            "name": "max_shares",
            "type": "u64"
          },
          {
            "name": "shares_sold",
            "type": "u64"
          },
          {
            "name": "bump",
            "type": "u8"
          }
        ]
      }
    }
  ]
}